cloudprime/__init__.py
cloudprime-1.1.1.dist-info/METADATA
cloudprime-1.1.1.dist-info/WHEEL
cloudprime-1.1.1.dist-info/top_level.txt
cloudprime-1.1.1.dist-info/RECORD
