Metadata-Version: 2.4
Name: cloudprime
Version: 1.1.1
Summary: A Python package for effortless file uploads and management via the CloudPrime, supporting images, videos, documents, presentations, spreadsheets, and all file types.
Author: IP Softech - Pratham Pansuriya
Author-email: ipsoftechsolutions@gmail.com
Classifier: Programming Language :: Python :: 3
Classifier: Programming Language :: Python :: 3.7
Classifier: Programming Language :: Python :: 3.8
Classifier: Programming Language :: Python :: 3.9
Classifier: Programming Language :: Python :: 3.10
Classifier: Programming Language :: Python :: 3.11
Classifier: License :: OSI Approved :: MIT License
Requires-Python: >=3.7
Requires-Dist: requests
Dynamic: author
Dynamic: author-email
Dynamic: classifier
Dynamic: description
Dynamic: description-content-type
Dynamic: requires-dist
Dynamic: requires-python
Dynamic: summary
